{
  "kit_name": "Fleet Travel",
  "file_key": "eQpOuv9h6qVnEwzvZ1iTDV",
  "figma_name": "Fleet_ Travel shopping Kit (Light)",
  "last_modified": "2026-02-13T18:28:43Z",
  "fetched_at": "2026-02-18T14:00:40.251071",
  "pages": [
    {
      "page_id": "1403:0",
      "page_name": "3B71FE",
      "skip_page": false,
      "screens": [
        {
          "id": "1767:0",
          "name": "message center",
          "type": "FRAME",
          "skip": false,
          "width": 1440.0,
          "height": 1024.0
        },
        {
          "id": "2388:15032",
          "name": "message center",
          "type": "FRAME",
          "skip": false,
          "width": 1024.0,
          "height": 1024.0
        },
        {
          "id": "1705:645",
          "name": "car rentals 2",
          "type": "FRAME",
          "skip": false,
          "width": 1440.0,
          "height": 3923.0
        },
        {
          "id": "2388:2350",
          "name": "car rentals 2",
          "type": "FRAME",
          "skip": false,
          "width": 1024.0,
          "height": 1855.0
        },
        {
          "id": "1705:3749",
          "name": "car rentals 3",
          "type": "FRAME",
          "skip": false,
          "width": 1440.0,
          "height": 5466.0
        },
        {
          "id": "2388:5481",
          "name": "car rentals 3",
          "type": "FRAME",
          "skip": false,
          "width": 1024.0,
          "height": 3262.0
        },
        {
          "id": "1708:336",
          "name": "card rentals 4",
          "type": "FRAME",
          "skip": false,
          "width": 1440.0,
          "height": 3793.0
        },
        {
          "id": "2388:7471",
          "name": "card rentals 4",
          "type": "FRAME",
          "skip": false,
          "width": 1024.0,
          "height": 3689.0
        },
        {
          "id": "1729:781",
          "name": "Car detail/desktop/light",
          "type": "FRAME",
          "skip": false,
          "width": 1440.0,
          "height": 5093.0
        },
        {
          "id": "2388:9721",
          "name": "Car detail/desktop/light",
          "type": "FRAME",
          "skip": false,
          "width": 1024.0,
          "height": 5149.0
        },
        {
          "id": "1741:0",
          "name": "car checkout",
          "type": "FRAME",
          "skip": false,
          "width": 1440.0,
          "height": 1837.0
        },
        {
          "id": "2388:13002",
          "name": "car checkout",
          "type": "FRAME",
          "skip": false,
          "width": 1024.0,
          "height": 1837.0
        },
        {
          "id": "1741:106",
          "name": "card checkout complete",
          "type": "FRAME",
          "skip": false,
          "width": 1440.0,
          "height": 1360.0
        },
        {
          "id": "2388:13950",
          "name": "card checkout complete",
          "type": "FRAME",
          "skip": false,
          "width": 1024.0,
          "height": 1248.0
        },
        {
          "id": "1702:0",
          "name": "car rentals 1",
          "type": "FRAME",
          "skip": false,
          "width": 1440.0,
          "height": 6923.0
        },
        {
          "id": "2388:41",
          "name": "car rentals 1",
          "type": "FRAME",
          "skip": false,
          "width": 1024.0,
          "height": 6489.0
        },
        {
          "id": "1770:60749",
          "name": "Wishlist",
          "type": "FRAME",
          "skip": false,
          "width": 1440.0,
          "height": 3448.0
        },
        {
          "id": "2388:16257",
          "name": "Wishlist",
          "type": "FRAME",
          "skip": false,
          "width": 1024.0,
          "height": 3284.35009765625
        },
        {
          "id": "1411:51651",
          "name": "Home",
          "type": "FRAME",
          "skip": false,
          "width": 1440.0,
          "height": 10962.0
        },
        {
          "id": "2364:116541",
          "name": "Home",
          "type": "FRAME",
          "skip": false,
          "width": 1025.0,
          "height": 9736.0
        },
        {
          "id": "1605:55606",
          "name": "Product category",
          "type": "FRAME",
          "skip": false,
          "width": 1440.0,
          "height": 6266.0
        },
        {
          "id": "2364:121570",
          "name": "Product category",
          "type": "FRAME",
          "skip": false,
          "width": 1024.0,
          "height": 5974.35009765625
        },
        {
          "id": "1609:1544",
          "name": "Product detail",
          "type": "FRAME",
          "skip": false,
          "width": 1440.0,
          "height": 5702.0
        },
        {
          "id": "2364:125066",
          "name": "Product detail",
          "type": "FRAME",
          "skip": false,
          "width": 1024.0,
          "height": 5022.35009765625
        },
        {
          "id": "1609:2285",
          "name": "Full photo grid",
          "type": "FRAME",
          "skip": false,
          "width": 1440.0,
          "height": 3580.0
        },
        {
          "id": "2364:129416",
          "name": "Full photo grid",
          "type": "FRAME",
          "skip": false,
          "width": 1024.0,
          "height": 3226.0
        },
        {
          "id": "1609:15255",
          "name": "Checkout",
          "type": "FRAME",
          "skip": false,
          "width": 1440.0,
          "height": 1837.0
        },
        {
          "id": "2364:130641",
          "name": "Checkout",
          "type": "FRAME",
          "skip": false,
          "width": 1024.0,
          "height": 1837.0
        },
        {
          "id": "1609:16047",
          "name": "checkout complete",
          "type": "FRAME",
          "skip": false,
          "width": 1440.0,
          "height": 1359.0
        },
        {
          "id": "2389:196027",
          "name": "checkout complete",
          "type": "FRAME",
          "skip": false,
          "width": 1024.0,
          "height": 1247.0
        },
        {
          "id": "1638:53893",
          "name": "Flight (round-trip)",
          "type": "FRAME",
          "skip": false,
          "width": 1440.0,
          "height": 3370.0
        },
        {
          "id": "2383:122119",
          "name": "Flight (round-trip)",
          "type": "FRAME",
          "skip": false,
          "width": 1024.0,
          "height": 3481.0
        },
        {
          "id": "1639:54817",
          "name": "Flight (One-way)",
          "type": "FRAME",
          "skip": false,
          "width": 1440.0,
          "height": 3186.0
        },
        {
          "id": "2383:124793",
          "name": "Flight (One-way)",
          "type": "FRAME",
          "skip": false,
          "width": 1024.0,
          "height": 3085.0
        },
        {
          "id": "1666:3006",
          "name": "product detail 2",
          "type": "FRAME",
          "skip": false,
          "width": 1440.0,
          "height": 5397.0
        },
        {
          "id": "2385:1806",
          "name": "product detail 2",
          "type": "FRAME",
          "skip": false,
          "width": 1024.0,
          "height": 5111.0
        },
        {
          "id": "1688:56225",
          "name": "checkout 2",
          "type": "FRAME",
          "skip": false,
          "width": 1440.0,
          "height": 1837.0
        },
        {
          "id": "2385:5944",
          "name": "checkout 2",
          "type": "FRAME",
          "skip": false,
          "width": 1024.0,
          "height": 1805.0
        },
        {
          "id": "1688:57257",
          "name": "checkout 2 complete",
          "type": "FRAME",
          "skip": false,
          "width": 1440.0,
          "height": 1440.0
        },
        {
          "id": "2385:7141",
          "name": "checkout 2 complete",
          "type": "FRAME",
          "skip": false,
          "width": 1024.0,
          "height": 1253.0
        },
        {
          "id": "1639:55560",
          "name": "flight",
          "type": "FRAME",
          "skip": false,
          "width": 1440.0,
          "height": 3701.0
        },
        {
          "id": "2383:120256",
          "name": "flight",
          "type": "FRAME",
          "skip": false,
          "width": 1024.0,
          "height": 3435.0
        },
        {
          "id": "1666:112",
          "name": "Product 2",
          "type": "FRAME",
          "skip": false,
          "width": 1440.0,
          "height": 5341.0
        },
        {
          "id": "2383:129114",
          "name": "Product 2",
          "type": "FRAME",
          "skip": false,
          "width": 1024.0,
          "height": 4814.35009765625
        },
        {
          "id": "1689:0",
          "name": "showmap",
          "type": "FRAME",
          "skip": false,
          "width": 1440.0,
          "height": 4312.0
        },
        {
          "id": "2385:11720",
          "name": "showmap",
          "type": "FRAME",
          "skip": false,
          "width": 1024.0,
          "height": 4100.35009765625
        },
        {
          "id": "2093:138",
          "name": "things to do header",
          "type": "FRAME",
          "skip": false,
          "width": 1440.0,
          "height": 1024.0
        },
        {
          "id": "2383:127160",
          "name": "things to do header",
          "type": "FRAME",
          "skip": false,
          "width": 1024.0,
          "height": 864.0
        },
        {
          "id": "1800:12",
          "name": "Language dropdown",
          "type": "FRAME",
          "skip": false,
          "width": 1440.0,
          "height": 1024.0
        },
        {
          "id": "1815:0",
          "name": "Notification drodown",
          "type": "FRAME",
          "skip": false,
          "width": 1440.0,
          "height": 1024.0
        },
        {
          "id": "1801:61742",
          "name": "help center",
          "type": "FRAME",
          "skip": false,
          "width": 1440.0,
          "height": 4295.0
        },
        {
          "id": "2388:25667",
          "name": "help center",
          "type": "FRAME",
          "skip": false,
          "width": 1024.0,
          "height": 4140.0
        },
        {
          "id": "1771:0",
          "name": "Wishlist",
          "type": "FRAME",
          "skip": false,
          "width": 1440.0,
          "height": 2412.0
        },
        {
          "id": "2388:18779",
          "name": "Wishlist",
          "type": "FRAME",
          "skip": false,
          "width": 1024.0,
          "height": 2303.0
        },
        {
          "id": "1810:695",
          "name": "host profile",
          "type": "FRAME",
          "skip": false,
          "width": 1440.0,
          "height": 4853.0
        },
        {
          "id": "2388:26835",
          "name": "host profile",
          "type": "FRAME",
          "skip": false,
          "width": 1024.0,
          "height": 4898.0
        },
        {
          "id": "1814:2313",
          "name": "list your property",
          "type": "FRAME",
          "skip": false,
          "width": 1440.0,
          "height": 2202.0
        },
        {
          "id": "2388:29956",
          "name": "list your property",
          "type": "FRAME",
          "skip": false,
          "width": 1024.0,
          "height": 2202.0
        },
        {
          "id": "2388:30224",
          "name": "list your property",
          "type": "FRAME",
          "skip": false,
          "width": 2648.0,
          "height": 375.0
        },
        {
          "id": "2388:22859",
          "name": "text input",
          "type": "FRAME",
          "skip": false,
          "width": 1440.0,
          "height": 1024.0
        },
        {
          "id": "2388:22862",
          "name": "text input",
          "type": "FRAME",
          "skip": false,
          "width": 1024.0,
          "height": 817.0
        },
        {
          "id": "2388:22860",
          "name": "calendar input",
          "type": "FRAME",
          "skip": false,
          "width": 1024.0,
          "height": 817.0
        },
        {
          "id": "2388:23166",
          "name": "calendar input",
          "type": "FRAME",
          "skip": false,
          "width": 1440.0,
          "height": 1024.0
        },
        {
          "id": "2388:23834",
          "name": "guest input",
          "type": "FRAME",
          "skip": false,
          "width": 1440.0,
          "height": 1024.0
        },
        {
          "id": "2388:24007",
          "name": "guest input",
          "type": "FRAME",
          "skip": false,
          "width": 1024.0,
          "height": 817.0
        },
        {
          "id": "1847:0",
          "name": "user profile",
          "type": "FRAME",
          "skip": false,
          "width": 1440.0,
          "height": 1647.0
        },
        {
          "id": "2389:140380",
          "name": "user profile",
          "type": "FRAME",
          "skip": false,
          "width": 1440.0,
          "height": 1024.0
        },
        {
          "id": "2388:31180",
          "name": "user profile",
          "type": "FRAME",
          "skip": false,
          "width": 1440.0,
          "height": 1373.0
        },
        {
          "id": "2388:31181",
          "name": "user profile",
          "type": "FRAME",
          "skip": false,
          "width": 1024.0,
          "height": 1373.0
        },
        {
          "id": "2389:141493",
          "name": "account setting",
          "type": "FRAME",
          "skip": false,
          "width": 1440.0,
          "height": 1567.0
        },
        {
          "id": "2389:141497",
          "name": "account setting",
          "type": "FRAME",
          "skip": false,
          "width": 1024.0,
          "height": 1551.0
        },
        {
          "id": "2389:141494",
          "name": "account setting",
          "type": "FRAME",
          "skip": false,
          "width": 1440.0,
          "height": 1406.0
        },
        {
          "id": "2389:141855",
          "name": "account setting",
          "type": "FRAME",
          "skip": false,
          "width": 1024.0,
          "height": 1390.0
        },
        {
          "id": "2389:141495",
          "name": "account setting",
          "type": "FRAME",
          "skip": false,
          "width": 1440.0,
          "height": 1443.0
        },
        {
          "id": "2389:142187",
          "name": "account setting",
          "type": "FRAME",
          "skip": false,
          "width": 1024.0,
          "height": 1427.0
        },
        {
          "id": "2389:141496",
          "name": "account setting",
          "type": "FRAME",
          "skip": false,
          "width": 1440.0,
          "height": 1826.0
        },
        {
          "id": "2389:142569",
          "name": "account setting",
          "type": "FRAME",
          "skip": false,
          "width": 1024.0,
          "height": 1810.0
        }
      ],
      "components": [
        {
          "id": "2388:15224",
          "name": "message center",
          "type": "FRAME",
          "skip": false,
          "width": 375.0,
          "height": 1049.0
        },
        {
          "id": "2388:16129",
          "name": "message center",
          "type": "FRAME",
          "skip": false,
          "width": 375.0,
          "height": 1049.0
        },
        {
          "id": "2388:3056",
          "name": "car rentals 2",
          "type": "FRAME",
          "skip": false,
          "width": 375.0,
          "height": 6050.0
        },
        {
          "id": "2388:6039",
          "name": "car rentals 3",
          "type": "FRAME",
          "skip": false,
          "width": 375.0,
          "height": 3003.0
        },
        {
          "id": "2388:8086",
          "name": "card rentals 4",
          "type": "FRAME",
          "skip": false,
          "width": 375.0,
          "height": 4330.0
        },
        {
          "id": "2388:10428",
          "name": "Car detail/desktop/light",
          "type": "FRAME",
          "skip": false,
          "width": 375.0,
          "height": 6350.0
        },
        {
          "id": "2388:13246",
          "name": "car checkout",
          "type": "FRAME",
          "skip": false,
          "width": 375.0,
          "height": 2903.0
        },
        {
          "id": "2388:14134",
          "name": "card checkout complete",
          "type": "FRAME",
          "skip": false,
          "width": 375.0,
          "height": 1770.0
        },
        {
          "id": "2388:645",
          "name": "car rentals 1",
          "type": "FRAME",
          "skip": false,
          "width": 375.0,
          "height": 7948.0
        },
        {
          "id": "2388:16739",
          "name": "Wishlist",
          "type": "FRAME",
          "skip": false,
          "width": 375.0,
          "height": 4293.3388671875
        },
        {
          "id": "2364:118959",
          "name": "Home",
          "type": "FRAME",
          "skip": false,
          "width": 375.0,
          "height": 13437.0
        },
        {
          "id": "2364:122466",
          "name": "Product category",
          "type": "FRAME",
          "skip": false,
          "width": 375.0,
          "height": 6821.3388671875
        },
        {
          "id": "2364:125815",
          "name": "Product detail",
          "type": "FRAME",
          "skip": false,
          "width": 375.0,
          "height": 6539.3388671875
        },
        {
          "id": "2364:127879",
          "name": "Product detail",
          "type": "FRAME",
          "skip": false,
          "width": 375.0,
          "height": 927.0
        },
        {
          "id": "2364:128839",
          "name": "Product detail",
          "type": "FRAME",
          "skip": false,
          "width": 375.0,
          "height": 1469.0
        },
        {
          "id": "2364:129075",
          "name": "Product detail",
          "type": "FRAME",
          "skip": false,
          "width": 375.0,
          "height": 927.0
        },
        {
          "id": "1957:8371",
          "name": "Showmap",
          "type": "INSTANCE",
          "skip": false,
          "width": 1440.0,
          "height": 1024.0
        },
        {
          "id": "2364:130101",
          "name": "Showmap",
          "type": "INSTANCE",
          "skip": false,
          "width": 1024.0,
          "height": 1024.0
        },
        {
          "id": "2364:130369",
          "name": "Showmap",
          "type": "INSTANCE",
          "skip": false,
          "width": 375.0,
          "height": 812.0
        },
        {
          "id": "2364:129562",
          "name": "Full photo grid",
          "type": "FRAME",
          "skip": false,
          "width": 375.0,
          "height": 1485.0
        },
        {
          "id": "1957:7718",
          "name": "Lightbox",
          "type": "INSTANCE",
          "skip": false,
          "width": 1440.0,
          "height": 1024.0
        },
        {
          "id": "2364:129987",
          "name": "Lightbox",
          "type": "INSTANCE",
          "skip": false,
          "width": 1024.0,
          "height": 768.0
        },
        {
          "id": "2364:130048",
          "name": "Lightbox",
          "type": "INSTANCE",
          "skip": false,
          "width": 375.0,
          "height": 812.0
        },
        {
          "id": "2364:130913",
          "name": "checkout complete",
          "type": "FRAME",
          "skip": false,
          "width": 375.0,
          "height": 3356.0
        },
        {
          "id": "2364:132932",
          "name": "checkout complete",
          "type": "FRAME",
          "skip": false,
          "width": 375.0,
          "height": 1801.0
        },
        {
          "id": "1940:3103",
          "name": "sign up",
          "type": "INSTANCE",
          "skip": false,
          "width": 375.0,
          "height": 812.0
        },
        {
          "id": "1940:3104",
          "name": "sign in",
          "type": "INSTANCE",
          "skip": false,
          "width": 375.0,
          "height": 812.0
        },
        {
          "id": "1940:3105",
          "name": "confirm",
          "type": "INSTANCE",
          "skip": false,
          "width": 375.0,
          "height": 812.0
        },
        {
          "id": "1940:3106",
          "name": "security code",
          "type": "INSTANCE",
          "skip": false,
          "width": 375.0,
          "height": 812.0
        },
        {
          "id": "1940:3107",
          "name": "sign up",
          "type": "INSTANCE",
          "skip": false,
          "width": 1024.0,
          "height": 817.0
        },
        {
          "id": "1940:3108",
          "name": "sign in",
          "type": "INSTANCE",
          "skip": false,
          "width": 1024.0,
          "height": 817.0
        },
        {
          "id": "1940:3109",
          "name": "confirm",
          "type": "INSTANCE",
          "skip": false,
          "width": 1024.0,
          "height": 817.0
        },
        {
          "id": "1940:3110",
          "name": "security code",
          "type": "INSTANCE",
          "skip": false,
          "width": 1024.0,
          "height": 817.0
        },
        {
          "id": "1940:3111",
          "name": "sign up",
          "type": "INSTANCE",
          "skip": false,
          "width": 1440.0,
          "height": 1024.0
        },
        {
          "id": "1940:3112",
          "name": "sign in",
          "type": "INSTANCE",
          "skip": false,
          "width": 1440.0,
          "height": 1024.0
        },
        {
          "id": "1940:3113",
          "name": "confirm",
          "type": "INSTANCE",
          "skip": false,
          "width": 1440.0,
          "height": 1024.0
        },
        {
          "id": "1940:3114",
          "name": "security code",
          "type": "INSTANCE",
          "skip": false,
          "width": 1440.0,
          "height": 1024.0
        },
        {
          "id": "2383:123673",
          "name": "Flight (round-trip)",
          "type": "FRAME",
          "skip": false,
          "width": 375.0,
          "height": 4766.0
        },
        {
          "id": "2383:125401",
          "name": "Flight (One-way)",
          "type": "FRAME",
          "skip": false,
          "width": 375.0,
          "height": 3911.0
        },
        {
          "id": "2385:4371",
          "name": "product detail 2",
          "type": "FRAME",
          "skip": false,
          "width": 375.0,
          "height": 7514.0
        },
        {
          "id": "2385:6204",
          "name": "checkout 2",
          "type": "FRAME",
          "skip": false,
          "width": 375.0,
          "height": 2911.0
        },
        {
          "id": "2385:7340",
          "name": "checkout 2 complete",
          "type": "FRAME",
          "skip": false,
          "width": 375.0,
          "height": 1802.0
        },
        {
          "id": "2383:120735",
          "name": "flight",
          "type": "FRAME",
          "skip": false,
          "width": 375.0,
          "height": 4229.0
        },
        {
          "id": "2385:41",
          "name": "Product 2",
          "type": "FRAME",
          "skip": false,
          "width": 375.0,
          "height": 5899.3388671875
        },
        {
          "id": "2385:12994",
          "name": "showmap",
          "type": "FRAME",
          "skip": false,
          "width": 375.0,
          "height": 3761.339111328125
        },
        {
          "id": "2383:127323",
          "name": "things to do header",
          "type": "FRAME",
          "skip": false,
          "width": 375.0,
          "height": 888.0
        },
        {
          "id": "2249:4",
          "name": "account dropdown",
          "type": "INSTANCE",
          "skip": false,
          "width": 1440.0,
          "height": 1024.0
        },
        {
          "id": "2388:20803",
          "name": "account dropdown",
          "type": "INSTANCE",
          "skip": false,
          "width": 1024.0,
          "height": 817.0
        },
        {
          "id": "2388:20941",
          "name": "account dropdown",
          "type": "INSTANCE",
          "skip": false,
          "width": 375.0,
          "height": 924.0
        },
        {
          "id": "2249:5810",
          "name": "dropdown 3",
          "type": "INSTANCE",
          "skip": false,
          "width": 1440.0,
          "height": 1024.0
        },
        {
          "id": "2388:21298",
          "name": "dropdown 4",
          "type": "INSTANCE",
          "skip": false,
          "width": 1024.0,
          "height": 864.0
        },
        {
          "id": "2388:21413",
          "name": "dropdown 5",
          "type": "INSTANCE",
          "skip": false,
          "width": 375.0,
          "height": 812.0
        },
        {
          "id": "2388:25953",
          "name": "help center",
          "type": "FRAME",
          "skip": false,
          "width": 375.0,
          "height": 4474.0
        },
        {
          "id": "2388:19160",
          "name": "Wishlist",
          "type": "FRAME",
          "skip": false,
          "width": 375.0,
          "height": 2719.0
        },
        {
          "id": "2388:27567",
          "name": "host profile",
          "type": "FRAME",
          "skip": false,
          "width": 375.0,
          "height": 4615.0
        },
        {
          "id": "2388:23014",
          "name": "text input",
          "type": "FRAME",
          "skip": false,
          "width": 375.0,
          "height": 924.0
        },
        {
          "id": "2388:31395",
          "name": "user profile",
          "type": "FRAME",
          "skip": false,
          "width": 375.0,
          "height": 1764.0
        },
        {
          "id": "2389:141676",
          "name": "account setting",
          "type": "FRAME",
          "skip": false,
          "width": 375.0,
          "height": 2167.0
        },
        {
          "id": "2389:142021",
          "name": "account setting",
          "type": "FRAME",
          "skip": false,
          "width": 375.0,
          "height": 1574.0
        },
        {
          "id": "2389:142378",
          "name": "account setting",
          "type": "FRAME",
          "skip": false,
          "width": 375.0,
          "height": 1679.0
        },
        {
          "id": "2389:142757",
          "name": "account setting",
          "type": "FRAME",
          "skip": false,
          "width": 375.0,
          "height": 2010.0
        },
        {
          "id": "5215:79252",
          "name": "3B71FE",
          "type": "TEXT",
          "skip": false,
          "width": 43.0,
          "height": 15.0
        },
        {
          "id": "5215:79253",
          "name": "3B71FE",
          "type": "TEXT",
          "skip": false,
          "width": 43.0,
          "height": 15.0
        },
        {
          "id": "5215:79254",
          "name": "3B71FE",
          "type": "TEXT",
          "skip": false,
          "width": 43.0,
          "height": 15.0
        },
        {
          "id": "5215:79255",
          "name": "3B71FE",
          "type": "TEXT",
          "skip": false,
          "width": 43.0,
          "height": 15.0
        },
        {
          "id": "5215:79256",
          "name": "A",
          "type": "TEXT",
          "skip": false,
          "width": 9.0,
          "height": 15.0
        },
        {
          "id": "5215:79257",
          "name": "3B71FE",
          "type": "TEXT",
          "skip": false,
          "width": 43.0,
          "height": 15.0
        },
        {
          "id": "5215:79258",
          "name": "3B71FE",
          "type": "TEXT",
          "skip": false,
          "width": 43.0,
          "height": 15.0
        },
        {
          "id": "5215:79259",
          "name": "3B71FE",
          "type": "TEXT",
          "skip": false,
          "width": 43.0,
          "height": 15.0
        },
        {
          "id": "5215:79260",
          "name": "3B71FE",
          "type": "TEXT",
          "skip": false,
          "width": 43.0,
          "height": 15.0
        },
        {
          "id": "5215:79261",
          "name": "3B71FE",
          "type": "TEXT",
          "skip": false,
          "width": 43.0,
          "height": 15.0
        },
        {
          "id": "5216:79263",
          "name": "image 1",
          "type": "RECTANGLE",
          "skip": false,
          "width": 1201.0,
          "height": 559.0
        }
      ],
      "screen_count": 77,
      "component_count": 72,
      "light_desktop_screens": 77,
      "light_desktop_components": 72
    },
    {
      "page_id": "1883:5729",
      "page_name": "\ud83d\ude80Stacks (P1)",
      "skip_page": false,
      "screens": [],
      "components": [
        {
          "id": "1885:67527",
          "name": "Hero",
          "type": "COMPONENT_SET",
          "skip": false,
          "width": 6709.0,
          "height": 968.0
        },
        {
          "id": "1888:1775",
          "name": "Adventure",
          "type": "COMPONENT_SET",
          "skip": false,
          "width": 6710.0,
          "height": 652.0
        },
        {
          "id": "1888:2799",
          "name": "Nav",
          "type": "COMPONENT_SET",
          "skip": false,
          "width": 6710.0,
          "height": 144.0
        },
        {
          "id": "2388:15643",
          "name": "Nav - full",
          "type": "COMPONENT_SET",
          "skip": false,
          "width": 6710.0,
          "height": 144.0
        },
        {
          "id": "1888:2800",
          "name": "Mobile nav - expanded",
          "type": "COMPONENT_SET",
          "skip": true,
          "width": 6710.0,
          "height": 844.0
        },
        {
          "id": "1889:66245",
          "name": "About",
          "type": "COMPONENT_SET",
          "skip": false,
          "width": 6710.0,
          "height": 1957.0
        },
        {
          "id": "1889:68321",
          "name": "How it work",
          "type": "COMPONENT_SET",
          "skip": false,
          "width": 6710.0,
          "height": 1566.0
        },
        {
          "id": "1889:68579",
          "name": "Image grids 01",
          "type": "COMPONENT_SET",
          "skip": false,
          "width": 6710.0,
          "height": 979.0
        },
        {
          "id": "1889:71748",
          "name": "Product card",
          "type": "COMPONENT_SET",
          "skip": false,
          "width": 6710.0,
          "height": 2890.0
        },
        {
          "id": "1904:3677",
          "name": "Get the app",
          "type": "COMPONENT_SET",
          "skip": false,
          "width": 6712.0,
          "height": 1065.0
        },
        {
          "id": "1904:4391",
          "name": "Property type",
          "type": "COMPONENT_SET",
          "skip": false,
          "width": 6742.0,
          "height": 749.0
        },
        {
          "id": "1904:5623",
          "name": "Explore nearby",
          "type": "COMPONENT_SET",
          "skip": false,
          "width": 6710.0,
          "height": 1096.0
        },
        {
          "id": "1904:6442",
          "name": "Best hosts",
          "type": "COMPONENT_SET",
          "skip": false,
          "width": 6710.0,
          "height": 804.0
        },
        {
          "id": "1904:6580",
          "name": "CTA",
          "type": "COMPONENT_SET",
          "skip": false,
          "width": 6728.0,
          "height": 1088.0
        },
        {
          "id": "1904:7665",
          "name": "Browse by category",
          "type": "COMPONENT_SET",
          "skip": false,
          "width": 6658.0,
          "height": 696.0
        },
        {
          "id": "1904:7976",
          "name": "Footer",
          "type": "COMPONENT_SET",
          "skip": false,
          "width": 6710.0,
          "height": 553.0
        },
        {
          "id": "1919:296",
          "name": "Modal",
          "type": "COMPONENT_SET",
          "skip": false,
          "width": 7070.0,
          "height": 4640.0
        },
        {
          "id": "1929:343",
          "name": "stays - hero header",
          "type": "COMPONENT_SET",
          "skip": false,
          "width": 6607.0,
          "height": 760.0
        },
        {
          "id": "1933:4233",
          "name": "stay card",
          "type": "COMPONENT_SET",
          "skip": false,
          "width": 6710.0,
          "height": 2044.0
        },
        {
          "id": "1933:11124",
          "name": "join our newsletter",
          "type": "COMPONENT_SET",
          "skip": false,
          "width": 6710.0,
          "height": 977.3390502929688
        },
        {
          "id": "1933:13740",
          "name": "superhost",
          "type": "COMPONENT_SET",
          "skip": false,
          "width": 6710.0,
          "height": 1112.0
        },
        {
          "id": "1935:25",
          "name": "Testimonials",
          "type": "COMPONENT_SET",
          "skip": false,
          "width": 6710.0,
          "height": 1100.0
        },
        {
          "id": "1951:406",
          "name": "Product Header",
          "type": "COMPONENT_SET",
          "skip": false,
          "width": 6710.0,
          "height": 2903.0
        },
        {
          "id": "1951:1286",
          "name": "product header",
          "type": "COMPONENT_SET",
          "skip": false,
          "width": 6710.0,
          "height": 1128.0
        },
        {
          "id": "1951:4535",
          "name": "Product detail 1",
          "type": "COMPONENT_SET",
          "skip": false,
          "width": 9010.0,
          "height": 1386.0
        },
        {
          "id": "1957:4876",
          "name": "user - review",
          "type": "COMPONENT_SET",
          "skip": false,
          "width": 6710.0,
          "height": 1357.0
        },
        {
          "id": "1957:7717",
          "name": "full photo grid",
          "type": "COMPONENT_SET",
          "skip": false,
          "width": 6710.0,
          "height": 3249.0
        },
        {
          "id": "1957:7976",
          "name": "Lightbox",
          "type": "COMPONENT_SET",
          "skip": false,
          "width": 6710.0,
          "height": 1056.0
        },
        {
          "id": "1957:10374",
          "name": "Showmap",
          "type": "COMPONENT_SET",
          "skip": false,
          "width": 6710.0,
          "height": 1056.0
        },
        {
          "id": "1959:5040",
          "name": "checkout",
          "type": "COMPONENT_SET",
          "skip": false,
          "width": 6710.0,
          "height": 2647.0
        },
        {
          "id": "2167:322",
          "name": "checkout - things to do",
          "type": "COMPONENT_SET",
          "skip": false,
          "width": 6678.0,
          "height": 2266.0
        },
        {
          "id": "1959:6779",
          "name": "check out 2",
          "type": "COMPONENT_SET",
          "skip": false,
          "width": 6710.0,
          "height": 1093.0
        },
        {
          "id": "2169:102",
          "name": "checkout success - things to do",
          "type": "COMPONENT_SET",
          "skip": false,
          "width": 6710.0,
          "height": 1093.0
        },
        {
          "id": "2049:3874",
          "name": "flight hero",
          "type": "COMPONENT_SET",
          "skip": false,
          "width": 6855.0,
          "height": 968.0
        },
        {
          "id": "2049:8640",
          "name": "flight search small",
          "type": "COMPONENT_SET",
          "skip": false,
          "width": 6840.0,
          "height": 848.0
        },
        {
          "id": "2089:12463",
          "name": "Flights card",
          "type": "COMPONENT_SET",
          "skip": false,
          "width": 6763.0,
          "height": 5106.0
        },
        {
          "id": "2093:8",
          "name": "things to do hero",
          "type": "COMPONENT_SET",
          "skip": false,
          "width": 6710.0,
          "height": 968.0
        },
        {
          "id": "2095:91009",
          "name": "experiences card",
          "type": "COMPONENT_SET",
          "skip": false,
          "width": 6682.0,
          "height": 2918.0
        },
        {
          "id": "2159:1381",
          "name": "things to do detail",
          "type": "COMPONENT_SET",
          "skip": false,
          "width": 6710.0,
          "height": 2869.0
        },
        {
          "id": "5215:79251",
          "name": "3B71FE",
          "type": "TEXT",
          "skip": false,
          "width": 43.0,
          "height": 15.0
        }
      ],
      "screen_count": 0,
      "component_count": 40,
      "light_desktop_screens": 0,
      "light_desktop_components": 39
    },
    {
      "page_id": "2189:96276",
      "page_name": "\ud83d\ude80Stacks (P2)",
      "skip_page": false,
      "screens": [],
      "components": [
        {
          "id": "2193:19",
          "name": "things to do - showmap",
          "type": "COMPONENT_SET",
          "skip": false,
          "width": 7860.0,
          "height": 1431.0
        },
        {
          "id": "2213:3327",
          "name": "car - showmap",
          "type": "COMPONENT_SET",
          "skip": false,
          "width": 7860.0,
          "height": 1431.0
        },
        {
          "id": "2198:99164",
          "name": "car hero",
          "type": "COMPONENT_SET",
          "skip": false,
          "width": 6710.0,
          "height": 968.0
        },
        {
          "id": "2198:99802",
          "name": "Popular destinations",
          "type": "COMPONENT_SET",
          "skip": false,
          "width": 6710.0,
          "height": 797.0
        },
        {
          "id": "2218:101682",
          "name": "checkout - car",
          "type": "COMPONENT_SET",
          "skip": false,
          "width": 6678.0,
          "height": 2258.0
        },
        {
          "id": "2219:294",
          "name": "checkout 2 - car",
          "type": "COMPONENT_SET",
          "skip": false,
          "width": 6710.0,
          "height": 1093.0
        },
        {
          "id": "2249:9527",
          "name": "dropdown 2",
          "type": "COMPONENT_SET",
          "skip": false,
          "width": 6710.0,
          "height": 1056.0
        },
        {
          "id": "2249:11719",
          "name": "support hero",
          "type": "COMPONENT_SET",
          "skip": false,
          "width": 6710.0,
          "height": 980.0
        },
        {
          "id": "2250:0",
          "name": "FAQ 02",
          "type": "COMPONENT_SET",
          "skip": false,
          "width": 6710.0,
          "height": 1505.0
        },
        {
          "id": "2252:502",
          "name": "profile",
          "type": "COMPONENT_SET",
          "skip": false,
          "width": 6710.0,
          "height": 2874.0
        },
        {
          "id": "2252:3240",
          "name": "List your property",
          "type": "COMPONENT_SET",
          "skip": false,
          "width": 6710.0,
          "height": 1971.0
        },
        {
          "id": "2252:10626",
          "name": "profile setting",
          "type": "COMPONENT_SET",
          "skip": false,
          "width": 6710.0,
          "height": 6178.0
        },
        {
          "id": "2308:116185",
          "name": "Hero text input",
          "type": "COMPONENT_SET",
          "skip": false,
          "width": 6709.0,
          "height": 968.0
        },
        {
          "id": "2308:121413",
          "name": "Calendar text input",
          "type": "COMPONENT_SET",
          "skip": false,
          "width": 6709.0,
          "height": 968.0
        },
        {
          "id": "2308:126856",
          "name": "guest input",
          "type": "COMPONENT_SET",
          "skip": false,
          "width": 5559.0,
          "height": 968.0
        },
        {
          "id": "2354:0",
          "name": "user profile 2",
          "type": "COMPONENT_SET",
          "skip": false,
          "width": 6710.0,
          "height": 1684.0
        },
        {
          "id": "2364:116408",
          "name": "Explore nearby",
          "type": "COMPONENT_SET",
          "skip": false,
          "width": 6710.0,
          "height": 1519.0
        },
        {
          "id": "2364:116409",
          "name": "Value props 01",
          "type": "COMPONENT_SET",
          "skip": false,
          "width": 6709.0,
          "height": 1332.0
        },
        {
          "id": "2364:116410",
          "name": "Clients 02",
          "type": "COMPONENT_SET",
          "skip": false,
          "width": 6710.0,
          "height": 852.0
        },
        {
          "id": "2364:116411",
          "name": "FAQ",
          "type": "COMPONENT_SET",
          "skip": false,
          "width": 6710.0,
          "height": 1108.0
        },
        {
          "id": "2364:116412",
          "name": "car search small",
          "type": "COMPONENT_SET",
          "skip": false,
          "width": 6710.0,
          "height": 312.0
        },
        {
          "id": "2364:116413",
          "name": "Car location",
          "type": "COMPONENT_SET",
          "skip": false,
          "width": 6710.0,
          "height": 3923.0
        },
        {
          "id": "2364:116414",
          "name": "Card card",
          "type": "COMPONENT_SET",
          "skip": false,
          "width": 6710.0,
          "height": 2355.0
        },
        {
          "id": "2364:116415",
          "name": "Car detail",
          "type": "COMPONENT_SET",
          "skip": false,
          "width": 6710.0,
          "height": 3128.0
        },
        {
          "id": "2364:116416",
          "name": "message",
          "type": "COMPONENT_SET",
          "skip": false,
          "width": 7860.0,
          "height": 968.0
        },
        {
          "id": "2364:116417",
          "name": "account dropdown",
          "type": "COMPONENT_SET",
          "skip": false,
          "width": 6710.0,
          "height": 1056.0
        },
        {
          "id": "2388:26414",
          "name": "Value props 04",
          "type": "COMPONENT_SET",
          "skip": false,
          "width": 6709.0,
          "height": 970.0
        }
      ],
      "screen_count": 0,
      "component_count": 27,
      "light_desktop_screens": 0,
      "light_desktop_components": 27
    },
    {
      "page_id": "1473:426",
      "page_name": "\u2699\ufe0fComponents",
      "skip_page": false,
      "screens": [
        {
          "id": "1855:7",
          "name": "icon boxes",
          "type": "FRAME",
          "skip": false,
          "width": 1440.0,
          "height": 464.0
        },
        {
          "id": "1885:64171",
          "name": "Icons",
          "type": "FRAME",
          "skip": false,
          "width": 8720.0,
          "height": 800.0
        },
        {
          "id": "2392:208295",
          "name": "guide",
          "type": "GROUP",
          "skip": false,
          "width": 617.1048583984375,
          "height": 163.0
        },
        {
          "id": "2392:208306",
          "name": "Icons",
          "type": "FRAME",
          "skip": false,
          "width": 2600.0,
          "height": 2071.0
        }
      ],
      "components": [
        {
          "id": "1770:60663",
          "name": "Nav/desktop-full/light",
          "type": "COMPONENT",
          "skip": false,
          "width": 1440.0,
          "height": 88.0
        },
        {
          "id": "1597:54338",
          "name": "avatar",
          "type": "COMPONENT_SET",
          "skip": false,
          "width": 132.0,
          "height": 72.0
        },
        {
          "id": "1475:49709",
          "name": "nearby card",
          "type": "COMPONENT_SET",
          "skip": false,
          "width": 836.0,
          "height": 358.0
        },
        {
          "id": "1444:46609",
          "name": "Product card/desktop/light",
          "type": "COMPONENT",
          "skip": false,
          "width": 1280.0,
          "height": 1286.0
        },
        {
          "id": "1438:3862",
          "name": "sub nav icon",
          "type": "COMPONENT_SET",
          "skip": false,
          "width": 536.0,
          "height": 120.0
        },
        {
          "id": "1438:4216",
          "name": "product card",
          "type": "COMPONENT_SET",
          "skip": false,
          "width": 576.0,
          "height": 794.0
        },
        {
          "id": "1466:251",
          "name": "property type card",
          "type": "COMPONENT_SET",
          "skip": false,
          "width": 919.0,
          "height": 722.0
        },
        {
          "id": "1473:561",
          "name": "host card",
          "type": "COMPONENT_SET",
          "skip": false,
          "width": 576.0,
          "height": 776.0
        },
        {
          "id": "1473:671",
          "name": "text dropdown",
          "type": "COMPONENT_SET",
          "skip": false,
          "width": 269.0,
          "height": 640.0
        },
        {
          "id": "1480:49680",
          "name": "category card",
          "type": "COMPONENT_SET",
          "skip": false,
          "width": 1197.0,
          "height": 292.0
        },
        {
          "id": "1527:50161",
          "name": "stay card",
          "type": "COMPONENT_SET",
          "skip": false,
          "width": 1718.0,
          "height": 449.0
        },
        {
          "id": "1527:51401",
          "name": "superhost card",
          "type": "COMPONENT_SET",
          "skip": false,
          "width": 995.0,
          "height": 250.0
        },
        {
          "id": "1597:53707",
          "name": "Hero header/desktop/light",
          "type": "COMPONENT",
          "skip": false,
          "width": 1440.0,
          "height": 1024.0
        },
        {
          "id": "1598:1546",
          "name": "confirm input",
          "type": "COMPONENT_SET",
          "skip": false,
          "width": 272.0,
          "height": 239.0
        },
        {
          "id": "1627:83",
          "name": "action icons",
          "type": "COMPONENT_SET",
          "skip": false,
          "width": 720.0,
          "height": 256.0
        },
        {
          "id": "1760:209",
          "name": "dropdown li",
          "type": "COMPONENT_SET",
          "skip": false,
          "width": 259.0,
          "height": 212.0
        },
        {
          "id": "1708:1131",
          "name": "car card/default/light",
          "type": "COMPONENT",
          "skip": false,
          "width": 352.0,
          "height": 393.0
        },
        {
          "id": "1708:1130",
          "name": "car card/hover/light",
          "type": "COMPONENT",
          "skip": false,
          "width": 352.0,
          "height": 393.0
        },
        {
          "id": "1705:3020",
          "name": "rent a car card/default/light",
          "type": "COMPONENT",
          "skip": false,
          "width": 544.0,
          "height": 225.0
        },
        {
          "id": "1705:3019",
          "name": "rent a car card/hover/light",
          "type": "COMPONENT",
          "skip": false,
          "width": 544.0,
          "height": 225.0
        },
        {
          "id": "1688:56853",
          "name": "Reserve box",
          "type": "COMPONENT",
          "skip": false,
          "width": 448.0,
          "height": 628.0
        },
        {
          "id": "1686:57031",
          "name": "review/desktop/light",
          "type": "COMPONENT",
          "skip": false,
          "width": 1440.0,
          "height": 980.0
        },
        {
          "id": "1671:55810",
          "name": "filter",
          "type": "COMPONENT",
          "skip": false,
          "width": 256.0,
          "height": 580.0
        },
        {
          "id": "1688:57459",
          "name": "Reserve box",
          "type": "COMPONENT",
          "skip": false,
          "width": 544.0,
          "height": 756.0
        },
        {
          "id": "1639:53650",
          "name": "flight card/default",
          "type": "COMPONENT",
          "skip": false,
          "width": 710.0,
          "height": 80.0
        },
        {
          "id": "1639:53649",
          "name": "flight card/hover",
          "type": "COMPONENT",
          "skip": false,
          "width": 710.0,
          "height": 80.0
        },
        {
          "id": "1639:53522",
          "name": "logo",
          "type": "COMPONENT",
          "skip": false,
          "width": 160.0,
          "height": 80.0
        },
        {
          "id": "1639:53520",
          "name": "flight logo/01",
          "type": "COMPONENT",
          "skip": false,
          "width": 96.0,
          "height": 24.0
        },
        {
          "id": "1636:54494",
          "name": "Component 2",
          "type": "COMPONENT_SET",
          "skip": false,
          "width": 96.0,
          "height": 241.0
        },
        {
          "id": "1671:55910",
          "name": "stop",
          "type": "COMPONENT",
          "skip": false,
          "width": 256.0,
          "height": 140.0
        },
        {
          "id": "1686:57703",
          "name": "thing to do card 2",
          "type": "COMPONENT_SET",
          "skip": false,
          "width": 786.0,
          "height": 1162.0
        },
        {
          "id": "1703:1929",
          "name": "Popular destinations card",
          "type": "COMPONENT_SET",
          "skip": false,
          "width": 768.0,
          "height": 369.0
        },
        {
          "id": "1729:1860",
          "name": "extras row",
          "type": "COMPONENT_SET",
          "skip": false,
          "width": 416.0,
          "height": 397.0
        },
        {
          "id": "1768:61122",
          "name": "host message card",
          "type": "COMPONENT_SET",
          "skip": false,
          "width": 373.0,
          "height": 519.0
        },
        {
          "id": "1805:62141",
          "name": "add guest/light",
          "type": "COMPONENT",
          "skip": false,
          "width": 346.0,
          "height": 61.0
        },
        {
          "id": "1805:62124",
          "name": "number",
          "type": "COMPONENT_SET",
          "skip": false,
          "width": 136.0,
          "height": 122.0
        },
        {
          "id": "1771:1804",
          "name": "Nav/default/desktop/light",
          "type": "COMPONENT",
          "skip": false,
          "width": 1440.0,
          "height": 88.0
        },
        {
          "id": "1883:6079",
          "name": "mega search box",
          "type": "COMPONENT_SET",
          "skip": false,
          "width": 1152.0,
          "height": 2126.0
        },
        {
          "id": "1885:65287",
          "name": "illustration card",
          "type": "COMPONENT_SET",
          "skip": false,
          "width": 2832.0,
          "height": 255.99998474121094
        },
        {
          "id": "1888:1294",
          "name": "illustration card/hover/desktop/on",
          "type": "COMPONENT",
          "skip": false,
          "width": 352.0,
          "height": 223.99998474121094
        },
        {
          "id": "1889:65604",
          "name": "about illustration",
          "type": "COMPONENT_SET",
          "skip": false,
          "width": 3242.0,
          "height": 732.0
        },
        {
          "id": "1904:2170",
          "name": "fake mobile ui",
          "type": "COMPONENT_SET",
          "skip": true,
          "width": 841.0,
          "height": 844.0
        },
        {
          "id": "1904:2487",
          "name": "phone mockup",
          "type": "COMPONENT_SET",
          "skip": false,
          "width": 672.0,
          "height": 2441.999755859375
        },
        {
          "id": "1906:644",
          "name": "modal",
          "type": "COMPONENT_SET",
          "skip": false,
          "width": 4372.0,
          "height": 1409.0
        },
        {
          "id": "1919:1223",
          "name": "mega search box - small",
          "type": "COMPONENT_SET",
          "skip": false,
          "width": 1152.0,
          "height": 984.0
        },
        {
          "id": "1930:758",
          "name": "breakcrumb",
          "type": "COMPONENT",
          "skip": false,
          "width": 1120.0,
          "height": 40.0
        },
        {
          "id": "1930:759",
          "name": "breakcrumb desktop",
          "type": "COMPONENT_SET",
          "skip": false,
          "width": 415.0,
          "height": 167.0
        },
        {
          "id": "1933:10723",
          "name": "illustration newsletter",
          "type": "COMPONENT_SET",
          "skip": false,
          "width": 1440.0,
          "height": 751.0
        },
        {
          "id": "1957:134",
          "name": "Host sticky sidebar",
          "type": "COMPONENT_SET",
          "skip": false,
          "width": 773.0,
          "height": 673.0
        },
        {
          "id": "1957:1594",
          "name": "review",
          "type": "COMPONENT_SET",
          "skip": false,
          "width": 1761.0,
          "height": 2495.0
        },
        {
          "id": "1959:771",
          "name": "price details",
          "type": "COMPONENT_SET",
          "skip": false,
          "width": 1198.0,
          "height": 788.0
        },
        {
          "id": "1959:1478",
          "name": "Confirm and pay",
          "type": "COMPONENT_SET",
          "skip": false,
          "width": 1138.0,
          "height": 1274.0
        },
        {
          "id": "1959:5192",
          "name": "congrats",
          "type": "COMPONENT_SET",
          "skip": false,
          "width": 1172.0,
          "height": 685.0
        },
        {
          "id": "1959:7153",
          "name": "mega search box - flights",
          "type": "COMPONENT_SET",
          "skip": false,
          "width": 1140.0,
          "height": 2474.0
        },
        {
          "id": "2049:6741",
          "name": "flight mega search 2",
          "type": "COMPONENT_SET",
          "skip": false,
          "width": 2952.0,
          "height": 1959.0
        },
        {
          "id": "1639:54750",
          "name": "flight card",
          "type": "COMPONENT_SET",
          "skip": false,
          "width": 1604.0,
          "height": 4597.0
        },
        {
          "id": "2089:13370",
          "name": "mega search box things to do",
          "type": "COMPONENT_SET",
          "skip": false,
          "width": 1152.0,
          "height": 2065.0
        },
        {
          "id": "2252:7654",
          "name": "Personal info",
          "type": "COMPONENT",
          "skip": false,
          "width": 1120.0,
          "height": 1205.0
        },
        {
          "id": "2252:7653",
          "name": "Login and security",
          "type": "COMPONENT",
          "skip": false,
          "width": 1120.0,
          "height": 1044.0
        },
        {
          "id": "2252:7652",
          "name": "Payment methods",
          "type": "COMPONENT",
          "skip": false,
          "width": 1120.0,
          "height": 1081.0
        },
        {
          "id": "2252:7651",
          "name": "Notification setting",
          "type": "COMPONENT",
          "skip": false,
          "width": 1120.0,
          "height": 1464.0
        },
        {
          "id": "2308:116184",
          "name": "search box text input",
          "type": "COMPONENT_SET",
          "skip": false,
          "width": 2524.0,
          "height": 1804.0
        },
        {
          "id": "2308:125902",
          "name": "search box text input",
          "type": "COMPONENT_SET",
          "skip": false,
          "width": 2524.0,
          "height": 1804.0
        },
        {
          "id": "2308:118927",
          "name": "search box calendar input",
          "type": "COMPONENT_SET",
          "skip": false,
          "width": 2524.0,
          "height": 2762.0
        },
        {
          "id": "2308:129598",
          "name": "cover",
          "type": "COMPONENT_SET",
          "skip": false,
          "width": 1314.0,
          "height": 2271.0
        },
        {
          "id": "2308:131171",
          "name": "top nav dropdown",
          "type": "COMPONENT_SET",
          "skip": false,
          "width": 830.0,
          "height": 653.0009765625
        },
        {
          "id": "2308:131263",
          "name": "drag and drop modal",
          "type": "COMPONENT_SET",
          "skip": false,
          "width": 695.0,
          "height": 1180.0009765625
        },
        {
          "id": "2198:98033",
          "name": "car mega search",
          "type": "COMPONENT_SET",
          "skip": false,
          "width": 1152.0,
          "height": 2610.0
        },
        {
          "id": "2209:2368",
          "name": "car search small box",
          "type": "COMPONENT_SET",
          "skip": false,
          "width": 1312.0,
          "height": 2328.0
        },
        {
          "id": "2249:2851",
          "name": "dropdown",
          "type": "COMPONENT_SET",
          "skip": false,
          "width": 816.0,
          "height": 405.0
        },
        {
          "id": "2249:3692",
          "name": "Nav",
          "type": "COMPONENT_SET",
          "skip": false,
          "width": 1472.0,
          "height": 2354.0
        },
        {
          "id": "2249:6221",
          "name": "travelers dropdown",
          "type": "COMPONENT_SET",
          "skip": false,
          "width": 324.0,
          "height": 704.0
        },
        {
          "id": "107:16",
          "name": "sample-ui",
          "type": "COMPONENT",
          "skip": false,
          "width": 318.0,
          "height": 318.0
        },
        {
          "id": "158:137",
          "name": "single-input-field",
          "type": "COMPONENT_SET",
          "skip": false,
          "width": 2169.0,
          "height": 284.0
        },
        {
          "id": "936:1187",
          "name": "small circle button",
          "type": "COMPONENT",
          "skip": false,
          "width": 32.0,
          "height": 32.0
        },
        {
          "id": "163:133",
          "name": "tab",
          "type": "COMPONENT_SET",
          "skip": false,
          "width": 377.0,
          "height": 72.0
        },
        {
          "id": "2392:208294",
          "name": "single-input-field",
          "type": "INSTANCE",
          "skip": false,
          "width": 300.0,
          "height": 48.0
        },
        {
          "id": "160:28",
          "name": "spacing/32",
          "type": "COMPONENT",
          "skip": false,
          "width": 32.0,
          "height": 32.0
        },
        {
          "id": "160:32",
          "name": "spacing/40",
          "type": "COMPONENT",
          "skip": false,
          "width": 40.0,
          "height": 40.0
        },
        {
          "id": "160:31",
          "name": "spacing/48",
          "type": "COMPONENT",
          "skip": false,
          "width": 48.0,
          "height": 48.0
        },
        {
          "id": "160:29",
          "name": "spacing/64",
          "type": "COMPONENT",
          "skip": false,
          "width": 64.0,
          "height": 64.0
        },
        {
          "id": "160:27",
          "name": "spacing/80",
          "type": "COMPONENT",
          "skip": false,
          "width": 80.0,
          "height": 80.0
        },
        {
          "id": "160:25",
          "name": "spacing/112",
          "type": "COMPONENT",
          "skip": false,
          "width": 112.0,
          "height": 112.0
        },
        {
          "id": "160:30",
          "name": "spacing/128",
          "type": "COMPONENT",
          "skip": false,
          "width": 128.0,
          "height": 128.0
        },
        {
          "id": "160:26",
          "name": "spacing/136",
          "type": "COMPONENT",
          "skip": false,
          "width": 136.0,
          "height": 136.0
        },
        {
          "id": "160:92",
          "name": "spacing/160",
          "type": "COMPONENT",
          "skip": false,
          "width": 160.0,
          "height": 160.0
        },
        {
          "id": "160:885",
          "name": "pricing/elements/feature-li",
          "type": "COMPONENT",
          "skip": false,
          "width": 276.0,
          "height": 24.0
        },
        {
          "id": "172:5",
          "name": "team logo/logo 01",
          "type": "COMPONENT",
          "skip": false,
          "width": 167.0,
          "height": 64.0
        },
        {
          "id": "172:2",
          "name": "team logo/logo 02",
          "type": "COMPONENT",
          "skip": false,
          "width": 166.0,
          "height": 64.0
        },
        {
          "id": "172:4",
          "name": "team logo/logo 03",
          "type": "COMPONENT",
          "skip": false,
          "width": 167.0,
          "height": 64.0
        },
        {
          "id": "172:3",
          "name": "team logo/logo 04",
          "type": "COMPONENT",
          "skip": false,
          "width": 167.0,
          "height": 64.0
        },
        {
          "id": "172:1",
          "name": "team logo/logo 05",
          "type": "COMPONENT",
          "skip": false,
          "width": 166.0,
          "height": 64.0
        },
        {
          "id": "172:0",
          "name": "team logo/logo 06",
          "type": "COMPONENT",
          "skip": false,
          "width": 167.0,
          "height": 64.0
        },
        {
          "id": "173:1297",
          "name": "input",
          "type": "COMPONENT_SET",
          "skip": false,
          "width": 2533.0,
          "height": 132.0
        },
        {
          "id": "2392:208302",
          "name": "single-input-field",
          "type": "FRAME",
          "skip": false,
          "width": 357.0,
          "height": 48.0
        },
        {
          "id": "237:17",
          "name": "placeholder/01",
          "type": "COMPONENT",
          "skip": false,
          "width": 600.0,
          "height": 600.0
        },
        {
          "id": "292:7085",
          "name": "testimonial/card",
          "type": "COMPONENT",
          "skip": false,
          "width": 262.0,
          "height": 285.0
        },
        {
          "id": "237:293",
          "name": "testimonial/card-center/light",
          "type": "COMPONENT",
          "skip": false,
          "width": 262.0,
          "height": 415.0
        },
        {
          "id": "292:3592",
          "name": "testimonial/card-center/dark",
          "type": "COMPONENT",
          "skip": true,
          "width": 262.0,
          "height": 415.0
        },
        {
          "id": "238:115",
          "name": "testimonial/card-medium",
          "type": "COMPONENT",
          "skip": false,
          "width": 548.0,
          "height": 412.0
        },
        {
          "id": "238:109",
          "name": "pagination/small",
          "type": "COMPONENT",
          "skip": false,
          "width": 68.0,
          "height": 8.0
        },
        {
          "id": "237:149",
          "name": "placeholder/02",
          "type": "COMPONENT",
          "skip": false,
          "width": 548.0,
          "height": 548.0
        },
        {
          "id": "238:806",
          "name": "icon/16/play",
          "type": "COMPONENT",
          "skip": false,
          "width": 16.0,
          "height": 16.0
        },
        {
          "id": "244:834",
          "name": "pagination",
          "type": "COMPONENT",
          "skip": false,
          "width": 4.0,
          "height": 80.0
        },
        {
          "id": "272:2886",
          "name": "Project Card/Style 01/Normal",
          "type": "COMPONENT",
          "skip": false,
          "width": 352.0,
          "height": 568.0
        },
        {
          "id": "272:2885",
          "name": "Project Card/Style 01/Hover",
          "type": "COMPONENT",
          "skip": false,
          "width": 352.0,
          "height": 568.0
        },
        {
          "id": "272:3058",
          "name": "Sub nav item",
          "type": "COMPONENT_SET",
          "skip": false,
          "width": 782.0,
          "height": 60.0
        },
        {
          "id": "303:4564",
          "name": "Slide/Card",
          "type": "COMPONENT",
          "skip": false,
          "width": 276.0,
          "height": 412.0
        },
        {
          "id": "313:2727",
          "name": "pricing/feature-row",
          "type": "COMPONENT",
          "skip": false,
          "width": 1120.0,
          "height": 64.0
        },
        {
          "id": "313:2670",
          "name": "pricing",
          "type": "COMPONENT_SET",
          "skip": false,
          "width": 1212.0,
          "height": 96.0
        },
        {
          "id": "355:82",
          "name": "single-input-field-2",
          "type": "COMPONENT",
          "skip": false,
          "width": 352.0,
          "height": 48.0
        },
        {
          "id": "413:6992",
          "name": "circle-button",
          "type": "COMPONENT_SET",
          "skip": false,
          "width": 542.0,
          "height": 713.0
        },
        {
          "id": "450:58",
          "name": "Toggle",
          "type": "COMPONENT_SET",
          "skip": false,
          "width": 802.0,
          "height": 996.0
        },
        {
          "id": "456:5515",
          "name": "Label",
          "type": "COMPONENT_SET",
          "skip": false,
          "width": 569.0,
          "height": 179.0
        },
        {
          "id": "456:5574",
          "name": "blog/card",
          "type": "COMPONENT",
          "skip": false,
          "width": 352.0,
          "height": 518.0
        },
        {
          "id": "457:50",
          "name": "simple-input",
          "type": "COMPONENT_SET",
          "skip": false,
          "width": 2922.0,
          "height": 104.0
        },
        {
          "id": "487:215",
          "name": "Mobile Menu",
          "type": "COMPONENT_SET",
          "skip": true,
          "width": 1847.0,
          "height": 1107.0
        },
        {
          "id": "533:54",
          "name": "Dot",
          "type": "COMPONENT_SET",
          "skip": false,
          "width": 60.0,
          "height": 40.0
        },
        {
          "id": "569:62",
          "name": "logo",
          "type": "COMPONENT_SET",
          "skip": false,
          "width": 535.0,
          "height": 121.0
        },
        {
          "id": "569:104",
          "name": "button",
          "type": "COMPONENT_SET",
          "skip": false,
          "width": 1340.0,
          "height": 552.0
        },
        {
          "id": "612:27",
          "name": "Dropdown/Light/Default",
          "type": "COMPONENT",
          "skip": false,
          "width": 191.0,
          "height": 48.0
        },
        {
          "id": "612:2254",
          "name": "Dropdown/Dark/Default",
          "type": "COMPONENT",
          "skip": true,
          "width": 191.0,
          "height": 48.0
        },
        {
          "id": "643:5508",
          "name": "text button",
          "type": "COMPONENT",
          "skip": false,
          "width": 127.0,
          "height": 24.0
        },
        {
          "id": "706:690",
          "name": "Component 3",
          "type": "COMPONENT_SET",
          "skip": false,
          "width": 2206.0,
          "height": 5604.0
        },
        {
          "id": "733:140",
          "name": "switch",
          "type": "COMPONENT_SET",
          "skip": false,
          "width": 96.0,
          "height": 220.0
        },
        {
          "id": "813:22111",
          "name": "couple arrows",
          "type": "COMPONENT_SET",
          "skip": false,
          "width": 112.0,
          "height": 154.0
        },
        {
          "id": "1206:5671",
          "name": "class",
          "type": "COMPONENT_SET",
          "skip": false,
          "width": 768.0,
          "height": 962.0
        },
        {
          "id": "1246:33455",
          "name": "blog",
          "type": "COMPONENT_SET",
          "skip": false,
          "width": 808.0,
          "height": 570.0
        },
        {
          "id": "1432:3",
          "name": "Fleet symbol",
          "type": "COMPONENT",
          "skip": false,
          "width": 32.0,
          "height": 32.0
        },
        {
          "id": "1889:65545",
          "name": "Arrows",
          "type": "COMPONENT_SET",
          "skip": false,
          "width": 120.0,
          "height": 149.0
        },
        {
          "id": "912:203",
          "name": "Dropdown_Product",
          "type": "COMPONENT_SET",
          "skip": false,
          "width": 383.0,
          "height": 937.0
        },
        {
          "id": "918:17987",
          "name": "Checkbox",
          "type": "COMPONENT_SET",
          "skip": false,
          "width": 381.0,
          "height": 100.0
        },
        {
          "id": "917:410",
          "name": "Your order item",
          "type": "COMPONENT",
          "skip": false,
          "width": 380.0,
          "height": 145.0
        },
        {
          "id": "912:1289",
          "name": "Process",
          "type": "COMPONENT_SET",
          "skip": false,
          "width": 864.0,
          "height": 361.0
        },
        {
          "id": "912:912",
          "name": "ratio button",
          "type": "COMPONENT_SET",
          "skip": false,
          "width": 94.0,
          "height": 56.0
        },
        {
          "id": "912:961",
          "name": "Ratio_Input_Field",
          "type": "COMPONENT_SET",
          "skip": false,
          "width": 201.0,
          "height": 210.0
        },
        {
          "id": "912:1139",
          "name": "Quantity",
          "type": "COMPONENT_SET",
          "skip": false,
          "width": 196.0,
          "height": 80.0
        },
        {
          "id": "1029:3431",
          "name": "Brand Logo/Paypal",
          "type": "COMPONENT",
          "skip": false,
          "width": 128.0,
          "height": 32.0
        },
        {
          "id": "1034:19406",
          "name": "Brand Logo/Visa",
          "type": "COMPONENT",
          "skip": false,
          "width": 128.0,
          "height": 32.0
        },
        {
          "id": "1034:19405",
          "name": "Brand Logo/master",
          "type": "COMPONENT",
          "skip": false,
          "width": 128.0,
          "height": 32.0
        }
      ],
      "screen_count": 4,
      "component_count": 140,
      "light_desktop_screens": 4,
      "light_desktop_components": 136
    },
    {
      "page_id": "2764:307093",
      "page_name": "-------------",
      "skip_page": false,
      "screens": [
        {
          "id": "2764:307094",
          "name": "thumbnail",
          "type": "FRAME",
          "skip": false,
          "width": 1920.0,
          "height": 960.0
        }
      ],
      "components": [],
      "screen_count": 1,
      "component_count": 0,
      "light_desktop_screens": 1,
      "light_desktop_components": 0
    },
    {
      "page_id": "401:3292",
      "page_name": "\ud83d\ude80Elements Guideline",
      "skip_page": false,
      "screens": [
        {
          "id": "401:3293",
          "name": "\ud83d\ude80Elements Guideline",
          "type": "FRAME",
          "skip": false,
          "width": 1440.0,
          "height": 10056.0
        }
      ],
      "components": [],
      "screen_count": 1,
      "component_count": 0,
      "light_desktop_screens": 1,
      "light_desktop_components": 0
    },
    {
      "page_id": "0:1",
      "page_name": "\ud83c\udd8eTypography",
      "skip_page": false,
      "screens": [],
      "components": [
        {
          "id": "1:2",
          "name": "Type System",
          "type": "FRAME",
          "skip": false,
          "width": 459.0,
          "height": 2272.0
        }
      ],
      "screen_count": 0,
      "component_count": 1,
      "light_desktop_screens": 0,
      "light_desktop_components": 1
    },
    {
      "page_id": "10:8",
      "page_name": "\ud83c\udfa8Colors",
      "skip_page": false,
      "screens": [],
      "components": [
        {
          "id": "10:23",
          "name": "Color System",
          "type": "FRAME",
          "skip": false,
          "width": 312.0,
          "height": 408.0
        },
        {
          "id": "15:32",
          "name": "Neutrals",
          "type": "FRAME",
          "skip": false,
          "width": 248.0,
          "height": 312.0
        }
      ],
      "screen_count": 0,
      "component_count": 2,
      "light_desktop_screens": 0,
      "light_desktop_components": 2
    },
    {
      "page_id": "674:8119",
      "page_name": "- - -",
      "skip_page": false,
      "screens": [],
      "components": [],
      "screen_count": 0,
      "component_count": 0,
      "light_desktop_screens": 0,
      "light_desktop_components": 0
    },
    {
      "page_id": "444:0",
      "page_name": "Prototype",
      "skip_page": false,
      "screens": [
        {
          "id": "444:121",
          "name": "Light/Value props 10",
          "type": "FRAME",
          "skip": false,
          "width": 1440.0,
          "height": 800.0
        },
        {
          "id": "444:182",
          "name": "Light/Value props 10",
          "type": "FRAME",
          "skip": false,
          "width": 1440.0,
          "height": 800.0
        },
        {
          "id": "444:245",
          "name": "Light/Value props 10",
          "type": "FRAME",
          "skip": false,
          "width": 1440.0,
          "height": 800.0
        },
        {
          "id": "444:305",
          "name": "Light/Value props 10",
          "type": "FRAME",
          "skip": false,
          "width": 1440.0,
          "height": 800.0
        }
      ],
      "components": [
        {
          "id": "444:1",
          "name": "Value props 10/Desktop/Light",
          "type": "INSTANCE",
          "skip": false,
          "width": 1440.0,
          "height": 800.0
        }
      ],
      "screen_count": 4,
      "component_count": 1,
      "light_desktop_screens": 4,
      "light_desktop_components": 1
    }
  ],
  "totals": {
    "pages": 10,
    "all_screens": 87,
    "all_components": 283,
    "light_desktop_screens": 87,
    "light_desktop_components": 278,
    "skipped_screens": 0,
    "skipped_components": 5
  }
}